saiku/__init__.py
saiku/actions/__init__.py
saiku/actions/chat.py
saiku/actions/execute_code.py
saiku/actions/speech_to_text.py
saiku/actions/text_to_image.py
saiku/actions/text_to_speech.py
saiku/actions/vision.py
saiku/actions/websocket.py
saiku/agents/__init__.py
saiku/agents/agent.py
saiku/interfaces/llm.py
saiku/islands/chat.html
saiku/llms/__init__.py
saiku/llms/google_vertex_ai_model.py
saiku/llms/hugging_face_model.py
saiku/llms/openai_model.py
saiku/utils.py
saiku_py-0.1.0.dist-info/LICENSE
saiku_py-0.1.0.dist-info/METADATA
saiku_py-0.1.0.dist-info/WHEEL
saiku_py-0.1.0.dist-info/entry_points.txt
saiku_py-0.1.0.dist-info/RECORD
