Metadata-Version: 2.1
Name: saiku-py
Version: 0.1.0
Summary: AI Agent capable of automating various tasks using openai API: Vision, Dalle3, Text To Seech, Speech to Text, Tool calls and Completions.
License: MIT
Author: Anis Marrouchi
Author-email: anismarrouchi@hotmail.com
Requires-Python: >=3.9,<4.0
Classifier: License :: OSI Approved :: MIT License
Classifier: Programming Language :: Python :: 3
Classifier: Programming Language :: Python :: 3.9
Classifier: Programming Language :: Python :: 3.10
Classifier: Programming Language :: Python :: 3.11
Classifier: Programming Language :: Python :: 3.12
Requires-Dist: aiohttp (>=3.9.0,<4.0.0)
Requires-Dist: aiohttp-cors (>=0.7.0,<0.8.0)
Requires-Dist: asyncio (>=3.4.3,<4.0.0)
Requires-Dist: click (>=8.1.7,<9.0.0)
Requires-Dist: eventlet (>=0.33.3,<0.34.0)
Requires-Dist: flask (>=3.0.0,<4.0.0)
Requires-Dist: flask-cors (>=4.0.0,<5.0.0)
Requires-Dist: markdown (>=3.5.1,<4.0.0)
Requires-Dist: nest-asyncio (>=1.5.8,<2.0.0)
Requires-Dist: openai (>=1.3.2,<2.0.0)
Requires-Dist: opencv-python (>=4.8.1.78,<5.0.0.0)
Requires-Dist: pandas (>=2.1.3,<3.0.0)
Requires-Dist: psutil (>=5.9.6,<6.0.0)
Requires-Dist: pygame (>=2.5.2,<3.0.0)
Requires-Dist: python-dotenv (>=0.19.0,<0.20.0)
Requires-Dist: python-socketio (>=5.10.0,<6.0.0)
Requires-Dist: requests (>=2.31.0,<3.0.0)
Requires-Dist: rich (>=13.7.0,<14.0.0)
Requires-Dist: sounddevice (>=0.4.6,<0.5.0)
Requires-Dist: wavio (>=0.0.8,<0.0.9)
Requires-Dist: youtube-dl (>=2021.12.17,<2022.0.0)
